sitools2/__init__.py
sitools2/clients/__init__.py
sitools2/clients/client_medoc.py
sitools2/clients/data.py
sitools2/clients/euvsyn_client_medoc.py
sitools2/clients/euvsyn_data.py
sitools2/clients/gaia_client_medoc.py
sitools2/clients/gaia_data.py
sitools2/clients/instrument_dataset.py
sitools2/clients/medoc_config.py
sitools2/clients/sdo_client_medoc.py
sitools2/clients/sdo_data.py
sitools2/clients/soho_client_medoc.py
sitools2/clients/soho_data.py
sitools2/clients/stereo_client_medoc.py
sitools2/clients/stereo_data.py
sitools2/core/__init__.py
sitools2/core/dataset.py
sitools2/core/field.py
sitools2/core/project.py
sitools2/core/query.py
sitools2/core/sitools2_instance.py
test_sitools2/__init__.py
test_sitools2/test_clients/__init__.py
test_sitools2/test_clients/test_client_medoc.py
test_sitools2/test_clients/test_data.py
test_sitools2/test_clients/test_euvsyn_client_medoc.py
test_sitools2/test_clients/test_euvsyn_data.py
test_sitools2/test_clients/test_gaia_client_medoc.py
test_sitools2/test_clients/test_gaia_data.py
test_sitools2/test_clients/test_sdo_client_medoc.py
test_sitools2/test_clients/test_sdo_data.py
test_sitools2/test_clients/test_soho_client_medoc.py
test_sitools2/test_clients/test_soho_data.py
test_sitools2/test_clients/test_stereo_client_medoc.py
test_sitools2/test_clients/test_stereo_data.py
test_sitools2/test_core/__init__.py
test_sitools2/test_core/test_dataset.py
test_sitools2/test_core/test_field.py
test_sitools2/test_core/test_project.py
test_sitools2/test_core/test_query.py
test_sitools2/test_core/test_sitools2_instance.py
pySitools2-1.0.2.dist-info/LICENCE
pySitools2-1.0.2.dist-info/METADATA
pySitools2-1.0.2.dist-info/WHEEL
pySitools2-1.0.2.dist-info/top_level.txt
pySitools2-1.0.2.dist-info/RECORD
