Metadata-Version: 2.1
Name: pySitools2
Version: 1.0.2
Summary: A generic python Sitools2 client with IDOC/MEDOC clients
Home-page: https://git.ias.u-psud.fr/medoc/PySitools2
Author: Nima TRAORE
Author-email: nima.traore@ias.u-psud.fr
License: GPLv3
Project-URL: MEDOC/IAS Web Interface, https://idoc-medoc.ias.u-psud.fr
Project-URL: Source, https://git.ias.u-psud.fr/medoc/PySitools2
Classifier: Development Status :: 5 - Production/Stable
Classifier: Programming Language :: Python
Classifier: Programming Language :: Python :: 3
Classifier: Programming Language :: Python :: 3 :: Only
Classifier: Programming Language :: Python :: 3.10
Classifier: Programming Language :: Python :: 3.11
Classifier: Programming Language :: Python :: 3.12
Classifier: Operating System :: OS Independent
Classifier: Environment :: Web Environment
Classifier: Intended Audience :: Developers
Classifier: Intended Audience :: Science/Research
Classifier: License :: OSI Approved :: GNU General Public License v3 (GPLv3)
License-File: LICENCE
Requires-Dist: pytest
Requires-Dist: pytest-cov
Requires-Dist: simplejson
Requires-Dist: future
Requires-Dist: astropy
Requires-Dist: matplotlib
Requires-Dist: sunpy
